pelican_vidme-0.1.1.dist-info/zip-safe
pelican_vidme-0.1.1.dist-info/WHEEL
pelican_vidme-0.1.1.dist-info/top_level.txt
pelican_vidme-0.1.1.dist-info/DESCRIPTION.rst
pelican_vidme-0.1.1.dist-info/metadata.json
pelican_vidme-0.1.1.dist-info/METADATA
pelican_vidme-0.1.1.dist-info/RECORD
pelican_vidme/vidme.py
pelican_vidme/__init__.py
