Metadata-Version: 2.0
Name: pelican-vidme
Version: 0.1.1
Summary: Easily embed Vidme videos in your posts
Home-page: https://github.com/chriscowley/pelican_vidme
Author: Chris Cowley
Author-email: chris@chriscowley.me.uk
License: MIT
Download-URL: https://github.com/chriscowley/pelican_vidme/archive/v0.1.1.zip
Platform: linux
Classifier: Development Status :: 3 - Alpha
Classifier: Operating System :: OS Independent
Classifier: Programming Language :: Python
Classifier: Programming Language :: Python :: 2.6
Classifier: Programming Language :: Python :: 2.7
Classifier: Programming Language :: Python :: 3
Classifier: Programming Language :: Python :: 3.1
Classifier: Programming Language :: Python :: 3.2
Classifier: Programming Language :: Python :: 3.3
Classifier: Programming Language :: Python :: Implementation :: CPython
Classifier: Intended Audience :: Developers
Classifier: License :: OSI Approved :: MIT License
Classifier: Topic :: Internet :: WWW/HTTP
Classifier: Topic :: Software Development :: Libraries :: Python Modules
Classifier: Topic :: Text Processing
Requires-Dist: pelican
